cotoba_cli/cli.py
cotoba_cli/cli_nlu.py
cotoba_cli/cli_platform.py
cotoba_cli/cli_test.py
cotoba_cli/cognito.py
cotoba_cli/config.py
cotoba_cli/configuration.py
cotoba_cli/error.py
cotoba_cli/nlu.py
cotoba_cli/platform.py
cotoba_cli/service/bot_test.py
cotoba_cli/session.py
cotoba_cli/util.py
cotoba_cli-1.3.2.dist-info/entry_points.txt
cotoba_cli-1.3.2.dist-info/WHEEL
cotoba_cli-1.3.2.dist-info/METADATA
cotoba_cli-1.3.2.dist-info/RECORD
