Metadata-Version: 2.1
Name: cotoba-cli
Version: 1.3.2
Summary: 
Requires-Python: >=3.6,<4.0
Classifier: Programming Language :: Python :: 3
Classifier: Programming Language :: Python :: 3.6
Classifier: Programming Language :: Python :: 3.7
Classifier: Programming Language :: Python :: 3.8
Classifier: Programming Language :: Python :: 3.9
Requires-Dist: boto3 (>=1.9,<2.0)
Requires-Dist: click (>=7.0,<8.0)
Requires-Dist: python-jose (>=3.0,<4.0)
Requires-Dist: pytz (>=2019,<2020)
Requires-Dist: requests (>=2.21,<3.0)
Requires-Dist: toml (>=0,<1)
